betterTUI/Screen.py
betterTUI/Wrapper.py
betterTUI/__init__.py
betterTUI/Basic/Box.py
betterTUI/Basic/Button.py
betterTUI/Basic/Counter.py
betterTUI/Basic/File.py
betterTUI/Basic/Input.py
betterTUI/Basic/Line.py
betterTUI/Basic/Select.py
betterTUI/Basic/SlimButton.py
betterTUI/Basic/Text.py
betterTUI/Basic/TextArea.py
betterTUI/Basic/__init__.py
betterTUI/Complex/Form.py
betterTUI/Complex/SearchBar.py
betterTUI/Complex/__init__.py
bettertui-0.0.51.dist-info/METADATA
bettertui-0.0.51.dist-info/WHEEL
bettertui-0.0.51.dist-info/licenses/LICENSE
bettertui-0.0.51.dist-info/RECORD
