Metadata-Version: 2.1
Name: betterTUI
Version: 0.0.51
Summary: collection of curses widgets for building TUI's
Project-URL: Homepage, https://github.com/Gomez0015/betterTUI
Project-URL: Bug Tracker, https://github.com/Gomez0015/betterTUI/issues
Author-email: "Oscar Gomez (Raxo)" <oscargomez.raxo@gmail.com>
License-File: LICENSE
Classifier: License :: OSI Approved :: GNU General Public License v3 (GPLv3)
Classifier: Operating System :: OS Independent
Classifier: Programming Language :: Python :: 3
Requires-Python: >=3.9
